esi_utils_rupture/__init__.py
esi_utils_rupture/base.py
esi_utils_rupture/constants.py
esi_utils_rupture/distance.py
esi_utils_rupture/edge_rupture.py
esi_utils_rupture/factory.py
esi_utils_rupture/gc2.py
esi_utils_rupture/origin.py
esi_utils_rupture/point_rupture.py
esi_utils_rupture/quad_rupture.py
esi_utils_rupture/tensor.py
esi_utils_rupture/utils.py
esi_utils_rupture-1.0.8.dist-info/licenses/LICENSE.md
esi_utils_rupture-1.0.8.dist-info/METADATA
esi_utils_rupture-1.0.8.dist-info/WHEEL
esi_utils_rupture-1.0.8.dist-info/top_level.txt
esi_utils_rupture-1.0.8.dist-info/RECORD
