Metadata-Version: 2.4
Name: esi-utils-rupture
Version: 1.0.8
Summary: USGS Earthquake Impact Utilities for Ruptures
Author-email: Eric Thompson <emthompsone@usgs.gov>, Bruce Worden <cbworden@contractor.usgs.gov>, Gabe Ferragut <gferragut@usgs.gov>
License-Expression: CC0-1.0
Requires-Python: >=3.11
License-File: LICENSE.md
Requires-Dist: decorator>=5.1
Requires-Dist: defusedxml>=0.7.1
Requires-Dist: esi-extern-openquake>=1.0.0
Requires-Dist: esi-utils-time>=1.0.0
Requires-Dist: esi-utils-vectors>=1.0.0
Requires-Dist: h5py>=3.7
Requires-Dist: numpy>=1.26
Requires-Dist: obspy>=1.3.0
Requires-Dist: openquake.engine>=3.23
Requires-Dist: numba
Requires-Dist: pandas>=1.0
Requires-Dist: psutil>=5.9
Requires-Dist: pyproj>=2.6.1
Requires-Dist: requests>2.28
Requires-Dist: toml>=0.10
Provides-Extra: dev
Requires-Dist: build>=0.7.0; extra == "dev"
Requires-Dist: black>=21; extra == "dev"
Requires-Dist: flake8>=3.9; extra == "dev"
Requires-Dist: ipython>=7.26; extra == "dev"
Provides-Extra: test
Requires-Dist: pytest>=6.2; extra == "test"
Requires-Dist: pytest-cov>=2.12; extra == "test"
Requires-Dist: pytest-console-scripts>=1.2; extra == "test"
Requires-Dist: vcrpy>=4.1; extra == "test"
Provides-Extra: build
Requires-Dist: build; extra == "build"
Requires-Dist: packaging>=24.2; extra == "build"
Requires-Dist: twine; extra == "build"
Requires-Dist: check-wheel-contents; extra == "build"
Dynamic: license-file
